README.md
setup.cfg
setup.py
sonipy/__init__.py
sonipy/sonify.py
sonipy/thinkdsp.py
sonipy/visualisation.py
sonipy.egg-info/PKG-INFO
sonipy.egg-info/SOURCES.txt
sonipy.egg-info/dependency_links.txt
sonipy.egg-info/requires.txt
sonipy.egg-info/top_level.txt
sonipy/scales/__init__.py
sonipy/scales/durations.py
sonipy/scales/frequency.py
sonipy/tests/__init__.py
sonipy/tests/test_durations.py
sonipy/tests/test_frequency.py
sonipy/tests/test_sonify.py
sonipy/tests/test_visualisation.py