Metadata-Version: 2.1
Name: sonipy
Version: 1.0
Summary: Sonification of 2D plots
Home-page: https://github.com/lockepatton/sonipy
Author: Locke Patton
Author-email: locke.patton@cfa.harvard.edu
License: UNKNOWN
Platform: UNKNOWN
Classifier: Programming Language :: Python :: 3.6
Classifier: Programming Language :: Python :: 3.7
Classifier: License :: OSI Approved :: MIT License
Classifier: Operating System :: OS Independent
